supersetpdfreport/__init__.py
supersetpdfreport/chart.py
supersetpdfreport/config.py
supersetpdfreport/logging.py
supersetpdfreport/nextcloud.py
supersetpdfreport/pdf_report.py
supersetpdfreport/process_job.py
supersetpdfreport/security.py
supersetpdfreport/send_mail.py
supersetpdfreport/task.py
supersetpdfreport/jobs/.gitkeep
supersetpdfreport/jobs/example_job.json
supersetpdfreport/latex/.gitkeep
supersetpdfreport/latex/images/.gitkeep
supersetpdfreport/latex/pdf/.gitkeep
supersetpdfreport/logs/.gitkeep
superset_pdf_report-0.6.8.3.dist-info/LICENSE
superset_pdf_report-0.6.8.3.dist-info/METADATA
superset_pdf_report-0.6.8.3.dist-info/WHEEL
superset_pdf_report-0.6.8.3.dist-info/top_level.txt
superset_pdf_report-0.6.8.3.dist-info/RECORD
