Metadata-Version: 2.1
Name: superset-pdf-report
Version: 0.6.8.3
Summary: For generating a pdf-report with apache-superset charts
Home-page: https://github.com/TheHassi/superset-pdf-report
Author: Andreas Hasselberg
Author-email: andreas.hasselberg@htw-dresden.de
License: UNKNOWN
Platform: UNKNOWN
Requires-Python: >=3.7
License-File: LICENSE
Requires-Dist: requests
Requires-Dist: httpx
Requires-Dist: webdavclient3
Requires-Dist: croniter
